vantage_agent/__init__.py
vantage_agent/exceptions.py
vantage_agent/helpers.py
vantage_agent/logger.py
vantage_agent/logicals/__init__.py
vantage_agent/logicals/health.py
vantage_agent/logicals/queue_actions.py
vantage_agent/logicals/scontrol.py
vantage_agent/logicals/squeue.py
vantage_agent/logicals/sync_partitions.py
vantage_agent/logicals/update.py
vantage_agent/logicals/vantage_api.py
vantage_agent/main.py
vantage_agent/plugin.py
vantage_agent/scheduler.py
vantage_agent/sentry.py
vantage_agent/settings.py
vantage_agent/tasks.py
vantage_agent/vantage_api_client.py
vantage_agent-3.2.1.dist-info/METADATA
vantage_agent-3.2.1.dist-info/WHEEL
vantage_agent-3.2.1.dist-info/entry_points.txt
vantage_agent-3.2.1.dist-info/RECORD
