Metadata-Version: 2.1
Name: vantage-agent
Version: 3.2.1
Summary: Vantage Agent
Author: Omnivector Solutions
Author-email: info@omnivector.solutions
Requires-Python: >=3.10,<4.0
Classifier: Programming Language :: Python :: 3
Classifier: Programming Language :: Python :: 3.10
Classifier: Programming Language :: Python :: 3.11
Classifier: Programming Language :: Python :: 3.12
Requires-Dist: APScheduler (==3.10.4)
Requires-Dist: httpx (>=0.27.0,<0.28.0)
Requires-Dist: jsondiff (>=2.2.0,<3.0.0)
Requires-Dist: loguru (>=0.7.2,<0.8.0)
Requires-Dist: py-buzz (>=4.1.0,<5.0.0)
Requires-Dist: pydantic (>=2.10.6,<3.0.0)
Requires-Dist: pydantic-settings (>=2.4.0,<3.0.0)
Requires-Dist: pyjwt (>=2.3.0,<3.0.0)
Requires-Dist: python-dotenv (>=1.0.1,<2.0.0)
Requires-Dist: python-jose (>=3.3.0,<4.0.0)
Requires-Dist: sentry-sdk (>=2.13.0,<3.0.0)
